Workbook

Sheet Startwerte
A1: CRUDE – Tabellenmodell Kapitel 1 (Roadmap 0.6)
A2: Gelbe Zellen mit blauer Schrift sind Stellschrauben: ändern, dann rechnen alle Blätter neu. Schwarze Zellen sind Formeln – nicht überschreiben.
A3: Werte aus GDD §15 (Startwerte Kapitel 1). Rot markierte Quellen sind Annahmen, die im GDD noch fehlen.
A4: Parameter | B4: Wert | C4: Einheit | D4: Quelle
A5: Bargeld zu Beginn | B5: 2000 | C5: $ | D5: GDD §15
A6: Bohrkosten je Bohrung bis 300 m (Seilschlag) | B6: 2000 | C6: $ | D6: GDD §15: 1.500–3.000 $ – hier die Mitte
A7: Pachtbonus je Parzelle (Randlage) | B7: 150 | C7: $ | D7: GDD §15: 50–300 $ in Randlage – hier die Mitte
A8: Pachtoptionen ohne Bonus zu Beginn | B8: 2 | C8: Parzellen | D8: GDD §13, Kapitel 1: Pachtoption auf 2 Parzellen
A9: Förderzins an Landbesitzer | B9: 0.125 | C9: der Förderung | D9: GDD §15: 1/8
A10: Anteil von Silas an den ersten Quellen | B10: 0.3 | C10: vom Gewinn | D10: GDD §15: 30 % (für den Bohrturm)
A11: Für wie viele Quellen Silas mitverdient | B11: 2 | C11: Quellen | D11: ANNAHME: GDD sagt nur „die ersten Quellen“
A12: Anfangsrate eines Funds | B12: 150 | C12: bbl/Tag | D12: GDD §15: 50–500 bbl/Tag (Gusher deutlich mehr)
A13: Rückgang der Förderung pro Quartal | B13: 0.12 | C13: pro Quartal | D13: GDD §15: 8–15 %
A14: Tage pro Runde (Quartal) | B14: 91 | C14: Tage | D14: GDD §2: Runde = Quartal
A15: Ölpreis ab Quelle | B15: 1 | C15: $/bbl | D15: ANNAHME: etwa Spindletop-Zeit um 1901; GDD nennt keinen Wert
A16: Transport mit dem Fuhrwerk | B16: 0.25 | C16: $/bbl | D16: ANNAHME: GDD §6 sagt nur „sehr hoch“
... A18: Kreditzins pro Jahr (Rating C) | B18: 0.1 | C18: pro Jahr | D18: GDD §15/§8: A 5 % · B 7 % · C 10 % · D 15 %
A19: Überschuss tilgt Kredit automatisch? (1 = ja, 0 = nein) | B19: 0 | D19: ANNAHME: Spielerentscheidung, hier als Schalter
A20: Trefferquote einer Wildcat-Bohrung | B20: 0.15 | D20: GDD §15: etwa 1 von 5 bis 1 von 10

Sheet Runden
A1: 16 Runden (Kapitel 1, Jahr 1–4, je Runde ein Quartal)
A2: Gelb = deine Eingaben je Runde: neue Parzellen pachten, bohren ja/nein, Ergebnis (Trocken/Fund) und Größe der Lagerstätte bei Fund. Vorgabe: Pechsträhne – jede Runde eine Bohrung, alle trocken.
A3: Ablauf je Runde: Pacht und Bohrung bezahlen, Zinsen zahlen, Öl aus früheren Funden verkaufen. Reicht das Geld nicht, springt die Bank bis zum Kreditrahmen ein. Ist auch der ausgeschöpft: PLEITE. Ein Fund fördert ab der Folgerunde.
A4: Runde | B4: Quartal | C4: Neue Parzellen pachten | D4: Bohren? (1/0) | E4: Ergebnis | F4: Lagerstätte bei Fund (bbl) | G4: Bargeld Anfang | H4: Schuld Anfang | I4: Pachtkosten | J4: Bohrkosten | K4: Zinsen | L4: Förderung (bbl) | M4: davon Silas-Quellen (bbl) | N4: Erlös nach Transport | O4: Förderzins Landbesitzer | P4: Anteil Silas | Q4: Cashflow der Runde | R4: Bargeld vor Kredit | S4: Neuer Kredit | T4: Tilgung | U4: Schuld Ende | V4: Bargeld Ende | W4: Trockenbohrungen bisher | X4: Status
A5: 1 | B5: Jahr 1 · Q1 | C5: 1 | D5: 1 | E5: Trocken | F5: 200000 | G5: =Startwerte!$B$5 | H5: 0 | I5: =(MAX(0,SUM($C$5:C5)-Startwerte!$B$8)-MAX(0,0-Startwerte!$B$8))*Startwerte!$B$7 | J5: =D5*Startwerte!$B$6 | K5: =H5*Startwerte!$B$18/4 | L5: =SUM(Quellen!$B$10:$Q$10) | M5: =SUMPRODUCT(Quellen!$B$10:$Q$10,Quellen!$B$6:$Q$6) | N5: =L5*(Startwerte!$B$15-Startwerte!$B$16) | O5: =L5*Startwerte!$B$15*Startwerte!$B$9 | P5: =M5*(Startwerte!$B$15-Startwerte!$B$16-Startwerte!$B$15*Startwerte!$B$9)*Startwerte!$B$10 | Q5: =N5-O5-P5-I5-J5-K5 | R5: =G5+Q5 | S5: =IF(R5<0,MIN(-R5,MAX(0,Startwerte!$B$17-H5)),0) | T5: =IF(AND(Startwerte!$B$19=1,R5>0),MIN(R5,H5),0) | U5: =H5+S5-T5 | V5: =R5+S5-T5 | W5: =0+IF(AND(D5=1,E5="Trocken"),1,0) | X5: =IF(OR(""="PLEITE",V5<0),"PLEITE","ok")
A6: 2 | B6: Jahr 1 · Q2 | C6: 1 | D6: 1 | E6: Trocken | F6: 200000 | G6: =V5 | H6: =U5 | I6: =(MAX(0,SUM($C$5:C6)-Startwerte!$B$8)-MAX(0,SUM($C$5:C5)-Startwerte!$B$8))*Startwerte!$B$7 | J6: =D6*Startwerte!$B$6 | K6: =H6*Startwerte!$B$18/4 | L6: =SUM(Quellen!$B$11:$Q$11) | M6: =SUMPRODUCT(Quellen!$B$11:$Q$11,Quellen!$B$6:$Q$6) | N6: =L6*(Startwerte!$B$15-Startwerte!$B$16) | O6: =L6*Startwerte!$B$15*Startwerte!$B$9 | P6: =M6*(Startwerte!$B$15-Startwerte!$B$16-Startwerte!$B$15*Startwerte!$B$9)*Startwerte!$B$10 | Q6: =N6-O6-P6-I6-J6-K6 | R6: =G6+Q6 | S6: =IF(R6<0,MIN(-R6,MAX(0,Startwerte!$B$17-H6)),0) | T6: =IF(AND(Startwerte!$B$19=1,R6>0),MIN(R6,H6),0) | U6: =H6+S6-T6 | V6: =R6+S6-T6 | W6: =W5+IF(AND(D6=1,E6="Trocken"),1,0) | X6: =IF(OR(X5="PLEITE",V6<0),"PLEITE","ok")
A7: 3 | B7: Jahr 1 · Q3 | C7: 1 | D7: 1 | E7: Trocken | F7: 200000 | G7: =V6 | H7: =U6 | I7: =(MAX(0,SUM($C$5:C7)-Startwerte!$B$8)-MAX(0,SUM($C$5:C6)-Startwerte!$B$8))*Startwerte!$B$7 | J7: =D7*Startwerte!$B$6 | K7: =H7*Startwerte!$B$18/4 | L7: =SUM(Quellen!$B$12:$Q$12) | M7: =SUMPRODUCT(Quellen!$B$12:$Q$12,Quellen!$B$6:$Q$6) | N7: =L7*(Startwerte!$B$15-Startwerte!$B$16) | O7: =L7*Startwerte!$B$15*Startwerte!$B$9 | P7: =M7*(Startwerte!$B$15-Startwerte!$B$16-Startwerte!$B$15*Startwerte!$B$9)*Startwerte!$B$10 | Q7: =N7-O7-P7-I7-J7-K7 | R7: =G7+Q7 | S7: =IF(R7<0,MIN(-R7,MAX(0,Startwerte!$B$17-H7)),0) | T7: =IF(AND(Startwerte!$B$19=1,R7>0),MIN(R7,H7),0) | U7: =H7+S7-T7 | V7: =R7+S7-T7 | W7: =W6+IF(AND(D7=1,E7="Trocken"),1,0) | X7: =IF(OR(X6="PLEITE",V7<0),"PLEITE","ok")
A8: 4 | B8: Jahr 1 · Q4 | C8: 1 | D8: 1 | E8: Trocken | F8: 200000 | G8: =V7 | H8: =U7 | I8: =(MAX(0,SUM($C$5:C8)-Startwerte!$B$8)-MAX(0,SUM($C$5:C7)-Startwerte!$B$8))*Startwerte!$B$7 | J8: =D8*Startwerte!$B$6 | K8: =H8*Startwerte!$B$18/4 | L8: =SUM(Quellen!$B$13:$Q$13) | M8: =SUMPRODUCT(Quellen!$B$13:$Q$13,Quellen!$B$6:$Q$6) | N8: =L8*(Startwerte!$B$15-Startwerte!$B$16) | O8: =L8*Startwerte!$B$15*Startwerte!$B$9 | P8: =M8*(Startwerte!$B$15-Startwerte!$B$16-Startwerte!$B$15*Startwerte!$B$9)*Startwerte!$B$10 | Q8: =N8-O8-P8-I8-J8-K8 | R8: =G8+Q8 | S8: =IF(R8<0,MIN(-R8,MAX(0,Startwerte!$B$17-H8)),0) | T8: =IF(AND(Startwerte!$B$19=1,R8>0),MIN(R8,H8),0) | U8: =H8+S8-T8 | V8: =R8+S8-T8 | W8: =W7+IF(AND(D8=1,E8="Trocken"),1,0) | X8: =IF(OR(X7="PLEITE",V8<0),"PLEITE","ok")
A9: 5 | B9: Jahr 2 · Q1 | C9: 1 | D9: 1 | E9: Trocken | F9: 200000 | G9: =V8 | H9: =U8 | I9: =(MAX(0,SUM($C$5:C9)-Startwerte!$B$8)-MAX(0,SUM($C$5:C8)-Startwerte!$B$8))*Startwerte!$B$7 | J9: =D9*Startwerte!$B$6 | K9: =H9*Startwerte!$B$18/4 | L9: =SUM(Quellen!$B$14:$Q$14) | M9: =SUMPRODUCT(Quellen!$B$14:$Q$14,Quellen!$B$6:$Q$6) | N9: =L9*(Startwerte!$B$15-Startwerte!$B$16) | O9: =L9*Startwerte!$B$15*Startwerte!$B$9 | P9: =M9*(Startwerte!$B$15-Startwerte!$B$16-Startwerte!$B$15*Startwerte!$B$9)*Startwerte!$B$10 | Q9: =N9-O9-P9-I9-J9-K9 | R9: =G9+Q9 | S9: =IF(R9<0,MIN(-R9,MAX(0,Startwerte!$B$17-H9)),0) | T9: =IF(AND(Startwerte!$B$19=1,R9>0),MIN(R9,H9),0) | U9: =H9+S9-T9 | V9: =R9+S9-T9 | W9: =W8+IF(AND(D9=1,E9="Trocken"),1,0) | X9: =IF(OR(X8="PLEITE",V9<0),"PLEITE","ok")
A10: 6 | B10: Jahr 2 · Q2 | C10: 1 | D10: 1 | E10: Trocken | F10: 200000 | G10: =V9 | H10: =U9 | I10: =(MAX(0,SUM($C$5:C10)-Startwerte!$B$8)-MAX(0,SUM($C$5:C9)-Startwerte!$B$8))*Startwerte!$B$7 | J10: =D10*Startwerte!$B$6 | K10: =H10*Startwerte!$B$18/4 | L10: =SUM(Quellen!$B$15:$Q$15) | M10: =SUMPRODUCT(Quellen!$B$15:$Q$15,Quellen!$B$6:$Q$6) | N10: =L10*(Startwerte!$B$15-Startwerte!$B$16) | O10: =L10*Startwerte!$B$15*Startwerte!$B$9 | P10: =M10*(Startwerte!$B$15-Startwerte!$B$16-Startwerte!$B$15*Startwerte!$B$9)*Startwerte!$B$10 | Q10: =N10-O10-P10-I10-J10-K10 | R10: =G10+Q10 | S10: =IF(R10<0,MIN(-R10,MAX(0,Startwerte!$B$17-H10)),0) | T10: =IF(AND(Startwerte!$B$19=1,R10>0),MIN(R10,H10),0) | U10: =H10+S10-T10 | V10: =R10+S10-T10 | W10: =W9+IF(AND(D10=1,E10="Trocken"),1,0) | X10: =IF(OR(X9="PLEITE",V10<0),"PLEITE","ok")
A11: 7 | B11: Jahr 2 · Q3 | C11: 1 | D11: 1 | E11: Trocken | F11: 200000 | G11: =V10 | H11: =U10 | I11: =(MAX(0,SUM($C$5:C11)-Startwerte!$B$8)-MAX(0,SUM($C$5:C10)-Startwerte!$B$8))*Startwerte!$B$7 | J11: =D11*Startwerte!$B$6 | K11: =H11*Startwerte!$B$18/4 | L11: =SUM(Quellen!$B$16:$Q$16) | M11: =SUMPRODUCT(Quellen!$B$16:$Q$16,Quellen!$B$6:$Q$6) | N11: =L11*(Startwerte!$B$15-Startwerte!$B$16) | O11: =L11*Startwerte!$B$15*Startwerte!$B$9 | P11: =M11*(Startwerte!$B$15-Startwerte!$B$16-Startwerte!$B$15*Startwerte!$B$9)*Startwerte!$B$10 | Q11: =N11-O11-P11-I11-J11-K11 | R11: =G11+Q11 | S11: =IF(R11<0,MIN(-R11,MAX(0,Startwerte!$B$17-H11)),0) | T11: =IF(AND(Startwerte!$B$19=1,R11>0),MIN(R11,H11),0) | U11: =H11+S11-T11 | V11: =R11+S11-T11 | W11: =W10+IF(AND(D11=1,E11="Trocken"),1,0) | X11: =IF(OR(X10="PLEITE",V11<0),"PLEITE","ok")
A12: 8 | B12: Jahr 2 · Q4 | C12: 1 | D12: 1 | E12: Trocken | F12: 200000 | G12: =V11 | H12: =U11 | I12: =(MAX(0,SUM($C$5:C12)-Startwerte!$B$8)-MAX(0,SUM($C$5:C11)-Startwerte!$B$8))*Startwerte!$B$7 | J12: =D12*Startwerte!$B$6 | K12: =H12*Startwerte!$B$18/4 | L12: =SUM(Quellen!$B$17:$Q$17) | M12: =SUMPRODUCT(Quellen!$B$17:$Q$17,Quellen!$B$6:$Q$6) | N12: =L12*(Startwerte!$B$15-Startwerte!$B$16) | O12: =L12*Startwerte!$B$15*Startwerte!$B$9 | P12: =M12*(Startwerte!$B$15-Startwerte!$B$16-Startwerte!$B$15*Startwerte!$B$9)*Startwerte!$B$10 | Q12: =N12-O12-P12-I12-J12-K12 | R12: =G12+Q12 | S12: =IF(R12<0,MIN(-R12,MAX(0,Startwerte!$B$17-H12)),0) | T12: =IF(AND(Startwerte!$B$19=1,R12>0),MIN(R12,H12),0) | U12: =H12+S12-T12 | V12: =R12+S12-T12 | W12: =W11+IF(AND(D12=1,E12="Trocken"),1,0) | X12: =IF(OR(X11="PLEITE",V12<0),"PLEITE","ok")
A13: 9 | B13: Jahr 3 · Q1 | C13: 1 | D13: 1 | E13: Trocken | F13: 200000 | G13: =V12 | H13: =U12 | I13: =(MAX(0,SUM($C$5:C13)-Startwerte!$B$8)-MAX(0,SUM($C$5:C12)-Startwerte!$B$8))*Startwerte!$B$7 | J13: =D13*Startwerte!$B$6 | K13: =H13*Startwerte!$B$18/4 | L13: =SUM(Quellen!$B$18:$Q$18) | M13: =SUMPRODUCT(Quellen!$B$18:$Q$18,Quellen!$B$6:$Q$6) | N13: =L13*(Startwerte!$B$15-Startwerte!$B$16) | O13: =L13*Startwerte!$B$15*Startwerte!$B$9 | P13: =M13*(Startwerte!$B$15-Startwerte!$B$16-Startwerte!$B$15*Startwerte!$B$9)*Startwerte!$B$10 | Q13: =N13-O13-P13-I13-J13-K13 | R13: =G13+Q13 | S13: =IF(R13<0,MIN(-R13,MAX(0,Startwerte!$B$17-H13)),0) | T13: =IF(AND(Startwerte!$B$19=1,R13>0),MIN(R13,H13),0) | U13: =H13+S13-T13 | V13: =R13+S13-T13 | W13: =W12+IF(AND(D13=1,E13="Trocken"),1,0) | X13: =IF(OR(X12="PLEITE",V13<0),"PLEITE","ok")
A14: 10 | B14: Jahr 3 · Q2 | C14: 1 | D14: 1 | E14: Trocken | F14: 200000 | G14: =V13 | H14: =U13 | I14: =(MAX(0,SUM($C$5:C14)-Startwerte!$B$8)-MAX(0,SUM($C$5:C13)-Startwerte!$B$8))*Startwerte!$B$7 | J14: =D14*Startwerte!$B$6 | K14: =H14*Startwerte!$B$18/4 | L14: =SUM(Quellen!$B$19:$Q$19) | M14: =SUMPRODUCT(Quellen!$B$19:$Q$19,Quellen!$B$6:$Q$6) | N14: =L14*(Startwerte!$B$15-Startwerte!$B$16) | O14: =L14*Startwerte!$B$15*Startwerte!$B$9 | P14: =M14*(Startwerte!$B$15-Startwerte!$B$16-Startwerte!$B$15*Startwerte!$B$9)*Startwerte!$B$10 | Q14: =N14-O14-P14-I14-J14-K14 | R14: =G14+Q14 | S14: =IF(R14<0,MIN(-R14,MAX(0,Startwerte!$B$17-H14)),0) | T14: =IF(AND(Startwerte!$B$19=1,R14>0),MIN(R14,H14),0) | U14: =H14+S14-T14 | V14: =R14+S14-T14 | W14: =W13+IF(AND(D14=1,E14="Trocken"),1,0) | X14: =IF(OR(X13="PLEITE",V14<0),"PLEITE","ok")
A15: 11 | B15: Jahr 3 · Q3 | C15: 1 | D15: 1 | E15: Trocken | F15: 200000 | G15: =V14 | H15: =U14 | I15: =(MAX(0,SUM($C$5:C15)-Startwerte!$B$8)-MAX(0,SUM($C$5:C14)-Startwerte!$B$8))*Startwerte!$B$7 | J15: =D15*Startwerte!$B$6 | K15: =H15*Startwerte!$B$18/4 | L15: =SUM(Quellen!$B$20:$Q$20) | M15: =SUMPRODUCT(Quellen!$B$20:$Q$20,Quellen!$B$6:$Q$6) | N15: =L15*(Startwerte!$B$15-Startwerte!$B$16) | O15: =L15*Startwerte!$B$15*Startwerte!$B$9 | P15: =M15*(Startwerte!$B$15-Startwerte!$B$16-Startwerte!$B$15*Startwerte!$B$9)*Startwerte!$B$10 | Q15: =N15-O15-P15-I15-J15-K15 | R15: =G15+Q15 | S15: =IF(R15<0,MIN(-R15,MAX(0,Startwerte!$B$17-H15)),0) | T15: =IF(AND(Startwerte!$B$19=1,R15>0),MIN(R15,H15),0) | U15: =H15+S15-T15 | V15: =R15+S15-T15 | W15: =W14+IF(AND(D15=1,E15="Trocken"),1,0) | X15: =IF(OR(X14="PLEITE",V15<0),"PLEITE","ok")
A16: 12 | B16: Jahr 3 · Q4 | C16: 1 | D16: 1 | E16: Trocken | F16: 200000 | G16: =V15 | H16: =U15 | I16: =(MAX(0,SUM($C$5:C16)-Startwerte!$B$8)-MAX(0,SUM($C$5:C15)-Startwerte!$B$8))*Startwerte!$B$7 | J16: =D16*Startwerte!$B$6 | K16: =H16*Startwerte!$B$18/4 | L16: =SUM(Quellen!$B$21:$Q$21) | M16: =SUMPRODUCT(Quellen!$B$21:$Q$21,Quellen!$B$6:$Q$6) | N16: =L16*(Startwerte!$B$15-Startwerte!$B$16) | O16: =L16*Startwerte!$B$15*Startwerte!$B$9 | P16: =M16*(Startwerte!$B$15-Startwerte!$B$16-Startwerte!$B$15*Startwerte!$B$9)*Startwerte!$B$10 | Q16: =N16-O16-P16-I16-J16-K16 | R16: =G16+Q16 | S16: =IF(R16<0,MIN(-R16,MAX(0,Startwerte!$B$17-H16)),0) | T16: =IF(AND(Startwerte!$B$19=1,R16>0),MIN(R16,H16),0) | U16: =H16+S16-T16 | V16: =R16+S16-T16 | W16: =W15+IF(AND(D16=1,E16="Trocken"),1,0) | X16: =IF(OR(X15="PLEITE",V16<0),"PLEITE","ok")
A17: 13 | B17: Jahr 4 · Q1 | C17: 1 | D17: 1 | E17: Trocken | F17: 200000 | G17: =V16 | H17: =U16 | I17: =(MAX(0,SUM($C$5:C17)-Startwerte!$B$8)-MAX(0,SUM($C$5:C16)-Startwerte!$B$8))*Startwerte!$B$7 | J17: =D17*Startwerte!$B$6 | K17: =H17*Startwerte!$B$18/4 | L17: =SUM(Quellen!$B$22:$Q$22) | M17: =SUMPRODUCT(Quellen!$B$22:$Q$22,Quellen!$B$6:$Q$6) | N17: =L17*(Startwerte!$B$15-Startwerte!$B$16) | O17: =L17*Startwerte!$B$15*Startwerte!$B$9 | P17: =M17*(Startwerte!$B$15-Startwerte!$B$16-Startwerte!$B$15*Startwerte!$B$9)*Startwerte!$B$10 | Q17: =N17-O17-P17-I17-J17-K17 | R17: =G17+Q17 | S17: =IF(R17<0,MIN(-R17,MAX(0,Startwerte!$B$17-H17)),0) | T17: =IF(AND(Startwerte!$B$19=1,R17>0),MIN(R17,H17),0) | U17: =H17+S17-T17 | V17: =R17+S17-T17 | W17: =W16+IF(AND(D17=1,E17="Trocken"),1,0) | X17: =IF(OR(X16="PLEITE",V17<0),"PLEITE","ok")
A18: 14 | B18: Jahr 4 · Q2 | C18: 1 | D18: 1 | E18: Trocken | F18: 200000 | G18: =V17 | H18: =U17 | I18: =(MAX(0,SUM($C$5:C18)-Startwerte!$B$8)-MAX(0,SUM($C$5:C17)-Startwerte!$B$8))*Startwerte!$B$7 | J18: =D18*Startwerte!$B$6 | K18: =H18*Startwerte!$B$18/4 | L18: =SUM(Quellen!$B$23:$Q$23) | M18: =SUMPRODUCT(Quellen!$B$23:$Q$23,Quellen!$B$6:$Q$6) | N18: =L18*(Startwerte!$B$15-Startwerte!$B$16) | O18: =L18*Startwerte!$B$15*Startwerte!$B$9 | P18: =M18*(Startwerte!$B$15-Startwerte!$B$16-Startwerte!$B$15*Startwerte!$B$9)*Startwerte!$B$10 | Q18: =N18-O18-P18-I18-J18-K18 | R18: =G18+Q18 | S18: =IF(R18<0,MIN(-R18,MAX(0,Startwerte!$B$17-H18)),0) | T18: =IF(AND(Startwerte!$B$19=1,R18>0),MIN(R18,H18),0) | U18: =H18+S18-T18 | V18: =R18+S18-T18 | W18: =W17+IF(AND(D18=1,E18="Trocken"),1,0) | X18: =IF(OR(X17="PLEITE",V18<0),"PLEITE","ok")
A19: 15 | B19: Jahr 4 · Q3 | C19: 1 | D19: 1 | E19: Trocken | F19: 200000 | G19: =V18 | H19: =U18 | I19: =(MAX(0,SUM($C$5:C19)-Startwerte!$B$8)-MAX(0,SUM($C$5:C18)-Startwerte!$B$8))*Startwerte!$B$7 | J19: =D19*Startwerte!$B$6 | K19: =H19*Startwerte!$B$18/4 | L19: =SUM(Quellen!$B$24:$Q$24) | M19: =SUMPRODUCT(Quellen!$B$24:$Q$24,Quellen!$B$6:$Q$6) | N19: =L19*(Startwerte!$B$15-Startwerte!$B$16) | O19: =L19*Startwerte!$B$15*Startwerte!$B$9 | P19: =M19*(Startwerte!$B$15-Startwerte!$B$16-Startwerte!$B$15*Startwerte!$B$9)*Startwerte!$B$10 | Q19: =N19-O19-P19-I19-J19-K19 | R19: =G19+Q19 | S19: =IF(R19<0,MIN(-R19,MAX(0,Startwerte!$B$17-H19)),0) | T19: =IF(AND(Startwerte!$B$19=1,R19>0),MIN(R19,H19),0) | U19: =H19+S19-T19 | V19: =R19+S19-T19 | W19: =W18+IF(AND(D19=1,E19="Trocken"),1,0) | X19: =IF(OR(X18="PLEITE",V19<0),"PLEITE","ok")
A20: 16 | B20: Jahr 4 · Q4 | C20: 1 | D20: 1 | E20: Trocken | F20: 200000 | G20: =V19 | H20: =U19 | I20: =(MAX(0,SUM($C$5:C20)-Startwerte!$B$8)-MAX(0,SUM($C$5:C19)-Startwerte!$B$8))*Startwerte!$B$7 | J20: =D20*Startwerte!$B$6 | K20: =H20*Startwerte!$B$18/4 | L20: =SUM(Quellen!$B$25:$Q$25) | M20: =SUMPRODUCT(Quellen!$B$25:$Q$25,Quellen!$B$6:$Q$6) | N20: =L20*(Startwerte!$B$15-Startwerte!$B$16) | O20: =L20*Startwerte!$B$15*Startwerte!$B$9 | P20: =M20*(Startwerte!$B$15-Startwerte!$B$16-Startwerte!$B$15*Startwerte!$B$9)*Startwerte!$B$10 | Q20: =N20-O20-P20-I20-J20-K20 | R20: =G20+Q20 | S20: =IF(R20<0,MIN(-R20,MAX(0,Startwerte!$B$17-H20)),0) | T20: =IF(AND(Startwerte!$B$19=1,R20>0),MIN(R20,H20),0) | U20: =H20+S20-T20 | V20: =R20+S20-T20 | W20: =W19+IF(AND(D20=1,E20="Trocken"),1,0) | X20: =IF(OR(X19="PLEITE",V20<0),"PLEITE","ok")
A22: Ergebnis
A23: Erste Runde mit PLEITE (0 = nie pleite) | G23: =IF(COUNTIF(X5:X20,"PLEITE")=0,0,16-COUNTIF(X5:X20,"PLEITE")+1)
A24: Trockenbohrungen, die Jacob noch bezahlen konnte | G24: =IF(G23=0,W20,IF(G23=1,0,INDEX(W5:W20,G23-1)))
A25: Bargeld am Ende von Runde 16 | G25: =V20
A26: Schuld am Ende von Runde 16 | G26: =U20
A27: Gefördertes Öl gesamt (bbl) | G27: =SUM(L5:L20)
A29: Hinweis: PLEITE heißt hier „Rechnung nicht mehr bezahlbar“. Im Spiel folgt laut GDD §8 erst eine Frist von 2 Runden (Notverkauf, Konsortium, Umschuldung). Die erste PLEITE-Runde ist also der Moment, in dem diese Frist beginnt.

Sheet Quellen
A1: Quellen: Förderung je Fund (Hilfsblatt, nur Formeln)
A2: GDD §15: q_t = q₀ · (1 − D)^t · R_t / R₀ – jede Quelle fördert ab der Runde nach dem Fund, höchstens bis die Lagerstätte leer ist.
A3: Quelle aus Runde | B3: 1 | C3: 2 | D3: 3 | E3: 4 | F3: 5 | G3: 6 | H3: 7 | I3: 8 | J3: 9 | K3: 10 | L3: 11 | M3: 12 | N3: 13 | O3: 14 | P3: 15 | Q3: 16
A4: Fund? (1/0) | B4: =IF(AND(Runden!$D$5=1,Runden!$E$5="Fund"),1,0) | C4: =IF(AND(Runden!$D$6=1,Runden!$E$6="Fund"),1,0) | D4: =IF(AND(Runden!$D$7=1,Runden!$E$7="Fund"),1,0) | E4: =IF(AND(Runden!$D$8=1,Runden!$E$8="Fund"),1,0) | F4: =IF(AND(Runden!$D$9=1,Runden!$E$9="Fund"),1,0) | G4: =IF(AND(Runden!$D$10=1,Runden!$E$10="Fund"),1,0) | H4: =IF(AND(Runden!$D$11=1,Runden!$E$11="Fund"),1,0) | I4: =IF(AND(Runden!$D$12=1,Runden!$E$12="Fund"),1,0) | J4: =IF(AND(Runden!$D$13=1,Runden!$E$13="Fund"),1,0) | K4: =IF(AND(Runden!$D$14=1,Runden!$E$14="Fund"),1,0) | L4: =IF(AND(Runden!$D$15=1,Runden!$E$15="Fund"),1,0) | M4: =IF(AND(Runden!$D$16=1,Runden!$E$16="Fund"),1,0) | N4: =IF(AND(Runden!$D$17=1,Runden!$E$17="Fund"),1,0) | O4: =IF(AND(Runden!$D$18=1,Runden!$E$18="Fund"),1,0) | P4: =IF(AND(Runden!$D$19=1,Runden!$E$19="Fund"),1,0) | Q4: =IF(AND(Runden!$D$20=1,Runden!$E$20="Fund"),1,0)
A5: Fund-Nummer | B5: =IF(B4=1,SUM($B$4:B4),0) | C5: =IF(C4=1,SUM($B$4:C4),0) | D5: =IF(D4=1,SUM($B$4:D4),0) | E5: =IF(E4=1,SUM($B$4:E4),0) | F5: =IF(F4=1,SUM($B$4:F4),0) | G5: =IF(G4=1,SUM($B$4:G4),0) | H5: =IF(H4=1,SUM($B$4:H4),0) | I5: =IF(I4=1,SUM($B$4:I4),0) | ... Q5: =IF(Q4=1,SUM($B$4:Q4),0)
A6: Silas verdient mit? | B6: =IF(AND(B4=1,B5<=Startwerte!$B$11),1,0) | C6: =IF(AND(C4=1,C5<=Startwerte!$B$11),1,0) | D6: =IF(AND(D4=1,D5<=Startwerte!$B$11),1,0) | E6: =IF(AND(E4=1,E5<=Startwerte!$B$11),1,0) | F6: =IF(AND(F4=1,F5<=Startwerte!$B$11),1,0) | G6: =IF(AND(G4=1,G5<=Startwerte!$B$11),1,0) | H6: =IF(AND(H4=1,H5<=Startwerte!$B$11),1,0) | I6: =IF(AND(I4=1,I5<=Startwerte!$B$11),1,0) | ... Q6: =IF(AND(Q4=1,Q5<=Startwerte!$B$11),1,0)
A7: Lagerstätte R₀ (bbl) | B7: =IF(B4=1,Runden!$F$5,0) | C7: =IF(C4=1,Runden!$F$6,0) | D7: =IF(D4=1,Runden!$F$7,0) | E7: =IF(E4=1,Runden!$F$8,0) | F7: =IF(F4=1,Runden!$F$9,0) | G7: =IF(G4=1,Runden!$F$10,0) | H7: =IF(H4=1,Runden!$F$11,0) | I7: =IF(I4=1,Runden!$F$12,0) | J7: =IF(J4=1,Runden!$F$13,0) | K7: =IF(K4=1,Runden!$F$14,0) | L7: =IF(L4=1,Runden!$F$15,0) | M7: =IF(M4=1,Runden!$F$16,0) | N7: =IF(N4=1,Runden!$F$17,0) | O7: =IF(O4=1,Runden!$F$18,0) | P7: =IF(P4=1,Runden!$F$19,0) | Q7: =IF(Q4=1,Runden!$F$20,0)
A9: Förderung je Runde (bbl)
A10: 1 | B10: =IF(AND(B$4=1,$A10>B$3,B$7>0),MIN(B30,Startwerte!$B$12*Startwerte!$B$14*(1-Startwerte!$B$13)^($A10-B$3-1)*B30/B$7),0) | C10: =IF(AND(C$4=1,$A10>C$3,C$7>0),MIN(C30,Startwerte!$B$12*Startwerte!$B$14*(1-Startwerte!$B$13)^($A10-C$3-1)*C30/C$7),0) | D10: =IF(AND(D$4=1,$A10>D$3,D$7>0),MIN(D30,Startwerte!$B$12*Startwerte!$B$14*(1-Startwerte!$B$13)^($A10-D$3-1)*D30/D$7),0) | E10: =IF(AND(E$4=1,$A10>E$3,E$7>0),MIN(E30,Startwerte!$B$12*Startwerte!$B$14*(1-Startwerte!$B$13)^($A10-E$3-1)*E30/E$7),0) | F10: =IF(AND(F$4=1,$A10>F$3,F$7>0),MIN(F30,Startwerte!$B$12*Startwerte!$B$14*(1-Startwerte!$B$13)^($A10-F$3-1)*F30/F$7),0) | G10: =IF(AND(G$4=1,$A10>G$3,G$7>0),MIN(G30,Startwerte!$B$12*Startwerte!$B$14*(1-Startwerte!$B$13)^($A10-G$3-1)*G30/G$7),0) | H10: =IF(AND(H$4=1,$A10>H$3,H$7>0),MIN(H30,Startwerte!$B$12*Startwerte!$B$14*(1-Startwerte!$B$13)^($A10-H$3-1)*H30/H$7),0) | I10: =IF(AND(I$4=1,$A10>I$3,I$7>0),MIN(I30,Startwerte!$B$12*Startwerte!$B$14*(1-Startwerte!$B$13)^($A10-I$3-1)*I30/I$7),0) | ... Q10: =IF(AND(Q$4=1,$A10>Q$3,Q$7>0),MIN(Q30,Startwerte!$B$12*Startwerte!$B$14*(1-Startwerte!$B$13)^($A10-Q$3-1)*Q30/Q$7),0)
A11: 2 | B11: =IF(AND(B$4=1,$A11>B$3,B$7>0),MIN(B31,Startwerte!$B$12*Startwerte!$B$14*(1-Startwerte!$B$13)^($A11-B$3-1)*B31/B$7),0) | C11: =IF(AND(C$4=1,$A11>C$3,C$7>0),MIN(C31,Startwerte!$B$12*Startwerte!$B$14*(1-Startwerte!$B$13)^($A11-C$3-1)*C31/C$7),0) | D11: =IF(AND(D$4=1,$A11>D$3,D$7>0),MIN(D31,Startwerte!$B$12*Startwerte!$B$14*(1-Startwerte!$B$13)^($A11-D$3-1)*D31/D$7),0) | E11: =IF(AND(E$4=1,$A11>E$3,E$7>0),MIN(E31,Startwerte!$B$12*Startwerte!$B$14*(1-Startwerte!$B$13)^($A11-E$3-1)*E31/E$7),0) | F11: =IF(AND(F$4=1,$A11>F$3,F$7>0),MIN(F31,Startwerte!$B$12*Startwerte!$B$14*(1-Startwerte!$B$13)^($A11-F$3-1)*F31/F$7),0) | G11: =IF(AND(G$4=1,$A11>G$3,G$7>0),MIN(G31,Startwerte!$B$12*Startwerte!$B$14*(1-Startwerte!$B$13)^($A11-G$3-1)*G31/G$7),0) | H11: =IF(AND(H$4=1,$A11>H$3,H$7>0),MIN(H31,Startwerte!$B$12*Startwerte!$B$14*(1-Startwerte!$B$13)^($A11-H$3-1)*H31/H$7),0) | I11: =IF(AND(I$4=1,$A11>I$3,I$7>0),MIN(I31,Startwerte!$B$12*Startwerte!$B$14*(1-Startwerte!$B$13)^($A11-I$3-1)*I31/I$7),0) | ... Q11: =IF(AND(Q$4=1,$A11>Q$3,Q$7>0),MIN(Q31,Startwerte!$B$12*Startwerte!$B$14*(1-Startwerte!$B$13)^($A11-Q$3-1)*Q31/Q$7),0)
A12: 3 | B12: =IF(AND(B$4=1,$A12>B$3,B$7>0),MIN(B32,Startwerte!$B$12*Startwerte!$B$14*(1-Startwerte!$B$13)^($A12-B$3-1)*B32/B$7),0) | C12: =IF(AND(C$4=1,$A12>C$3,C$7>0),MIN(C32,Startwerte!$B$12*Startwerte!$B$14*(1-Startwerte!$B$13)^($A12-C$3-1)*C32/C$7),0) | D12: =IF(AND(D$4=1,$A12>D$3,D$7>0),MIN(D32,Startwerte!$B$12*Startwerte!$B$14*(1-Startwerte!$B$13)^($A12-D$3-1)*D32/D$7),0) | E12: =IF(AND(E$4=1,$A12>E$3,E$7>0),MIN(E32,Startwerte!$B$12*Startwerte!$B$14*(1-Startwerte!$B$13)^($A12-E$3-1)*E32/E$7),0) | F12: =IF(AND(F$4=1,$A12>F$3,F$7>0),MIN(F32,Startwerte!$B$12*Startwerte!$B$14*(1-Startwerte!$B$13)^($A12-F$3-1)*F32/F$7),0) | G12: =IF(AND(G$4=1,$A12>G$3,G$7>0),MIN(G32,Startwerte!$B$12*Startwerte!$B$14*(1-Startwerte!$B$13)^($A12-G$3-1)*G32/G$7),0) | H12: =IF(AND(H$4=1,$A12>H$3,H$7>0),MIN(H32,Startwerte!$B$12*Startwerte!$B$14*(1-Startwerte!$B$13)^($A12-H$3-1)*H32/H$7),0) | I12: =IF(AND(I$4=1,$A12>I$3,I$7>0),MIN(I32,Startwerte!$B$12*Startwerte!$B$14*(1-Startwerte!$B$13)^($A12-I$3-1)*I32/I$7),0) | ... Q12: =IF(AND(Q$4=1,$A12>Q$3,Q$7>0),MIN(Q32,Startwerte!$B$12*Startwerte!$B$14*(1-Startwerte!$B$13)^($A12-Q$3-1)*Q32/Q$7),0)
A13: 4 | B13: =IF(AND(B$4=1,$A13>B$3,B$7>0),MIN(B33,Startwerte!$B$12*Startwerte!$B$14*(1-Startwerte!$B$13)^($A13-B$3-1)*B33/B$7),0) | C13: =IF(AND(C$4=1,$A13>C$3,C$7>0),MIN(C33,Startwerte!$B$12*Startwerte!$B$14*(1-Startwerte!$B$13)^($A13-C$3-1)*C33/C$7),0) | D13: =IF(AND(D$4=1,$A13>D$3,D$7>0),MIN(D33,Startwerte!$B$12*Startwerte!$B$14*(1-Startwerte!$B$13)^($A13-D$3-1)*D33/D$7),0) | E13: =IF(AND(E$4=1,$A13>E$3,E$7>0),MIN(E33,Startwerte!$B$12*Startwerte!$B$14*(1-Startwerte!$B$13)^($A13-E$3-1)*E33/E$7),0) | F13: =IF(AND(F$4=1,$A13>F$3,F$7>0),MIN(F33,Startwerte!$B$12*Startwerte!$B$14*(1-Startwerte!$B$13)^($A13-F$3-1)*F33/F$7),0) | G13: =IF(AND(G$4=1,$A13>G$3,G$7>0),MIN(G33,Startwerte!$B$12*Startwerte!$B$14*(1-Startwerte!$B$13)^($A13-G$3-1)*G33/G$7),0) | H13: =IF(AND(H$4=1,$A13>H$3,H$7>0),MIN(H33,Startwerte!$B$12*Startwerte!$B$14*(1-Startwerte!$B$13)^($A13-H$3-1)*H33/H$7),0) | I13: =IF(AND(I$4=1,$A13>I$3,I$7>0),MIN(I33,Startwerte!$B$12*Startwerte!$B$14*(1-Startwerte!$B$13)^($A13-I$3-1)*I33/I$7),0) | ... Q13: =IF(AND(Q$4=1,$A13>Q$3,Q$7>0),MIN(Q33,Startwerte!$B$12*Startwerte!$B$14*(1-Startwerte!$B$13)^($A13-Q$3-1)*Q33/Q$7),0)
A14: 5 | B14: =IF(AND(B$4=1,$A14>B$3,B$7>0),MIN(B34,Startwerte!$B$12*Startwerte!$B$14*(1-Startwerte!$B$13)^($A14-B$3-1)*B34/B$7),0) | C14: =IF(AND(C$4=1,$A14>C$3,C$7>0),MIN(C34,Startwerte!$B$12*Startwerte!$B$14*(1-Startwerte!$B$13)^($A14-C$3-1)*C34/C$7),0) | D14: =IF(AND(D$4=1,$A14>D$3,D$7>0),MIN(D34,Startwerte!$B$12*Startwerte!$B$14*(1-Startwerte!$B$13)^($A14-D$3-1)*D34/D$7),0) | E14: =IF(AND(E$4=1,$A14>E$3,E$7>0),MIN(E34,Startwerte!$B$12*Startwerte!$B$14*(1-Startwerte!$B$13)^($A14-E$3-1)*E34/E$7),0) | F14: =IF(AND(F$4=1,$A14>F$3,F$7>0),MIN(F34,Startwerte!$B$12*Startwerte!$B$14*(1-Startwerte!$B$13)^($A14-F$3-1)*F34/F$7),0) | G14: =IF(AND(G$4=1,$A14>G$3,G$7>0),MIN(G34,Startwerte!$B$12*Startwerte!$B$14*(1-Startwerte!$B$13)^($A14-G$3-1)*G34/G$7),0) | H14: =IF(AND(H$4=1,$A14>H$3,H$7>0),MIN(H34,Startwerte!$B$12*Startwerte!$B$14*(1-Startwerte!$B$13)^($A14-H$3-1)*H34/H$7),0) | I14: =IF(AND(I$4=1,$A14>I$3,I$7>0),MIN(I34,Startwerte!$B$12*Startwerte!$B$14*(1-Startwerte!$B$13)^($A14-I$3-1)*I34/I$7),0) | ... Q14: =IF(AND(Q$4=1,$A14>Q$3,Q$7>0),MIN(Q34,Startwerte!$B$12*Startwerte!$B$14*(1-Startwerte!$B$13)^($A14-Q$3-1)*Q34/Q$7),0)
A15: 6 | B15: =IF(AND(B$4=1,$A15>B$3,B$7>0),MIN(B35,Startwerte!$B$12*Startwerte!$B$14*(1-Startwerte!$B$13)^($A15-B$3-1)*B35/B$7),0) | C15: =IF(AND(C$4=1,$A15>C$3,C$7>0),MIN(C35,Startwerte!$B$12*Startwerte!$B$14*(1-Startwerte!$B$13)^($A15-C$3-1)*C35/C$7),0) | D15: =IF(AND(D$4=1,$A15>D$3,D$7>0),MIN(D35,Startwerte!$B$12*Startwerte!$B$14*(1-Startwerte!$B$13)^($A15-D$3-1)*D35/D$7),0) | E15: =IF(AND(E$4=1,$A15>E$3,E$7>0),MIN(E35,Startwerte!$B$12*Startwerte!$B$14*(1-Startwerte!$B$13)^($A15-E$3-1)*E35/E$7),0) | F15: =IF(AND(F$4=1,$A15>F$3,F$7>0),MIN(F35,Startwerte!$B$12*Startwerte!$B$14*(1-Startwerte!$B$13)^($A15-F$3-1)*F35/F$7),0) | G15: =IF(AND(G$4=1,$A15>G$3,G$7>0),MIN(G35,Startwerte!$B$12*Startwerte!$B$14*(1-Startwerte!$B$13)^($A15-G$3-1)*G35/G$7),0) | H15: =IF(AND(H$4=1,$A15>H$3,H$7>0),MIN(H35,Startwerte!$B$12*Startwerte!$B$14*(1-Startwerte!$B$13)^($A15-H$3-1)*H35/H$7),0) | I15: =IF(AND(I$4=1,$A15>I$3,I$7>0),MIN(I35,Startwerte!$B$12*Startwerte!$B$14*(1-Startwerte!$B$13)^($A15-I$3-1)*I35/I$7),0) | ... Q15: =IF(AND(Q$4=1,$A15>Q$3,Q$7>0),MIN(Q35,Startwerte!$B$12*Startwerte!$B$14*(1-Startwerte!$B$13)^($A15-Q$3-1)*Q35/Q$7),0)
A16: 7 | B16: =IF(AND(B$4=1,$A16>B$3,B$7>0),MIN(B36,Startwerte!$B$12*Startwerte!$B$14*(1-Startwerte!$B$13)^($A16-B$3-1)*B36/B$7),0) | C16: =IF(AND(C$4=1,$A16>C$3,C$7>0),MIN(C36,Startwerte!$B$12*Startwerte!$B$14*(1-Startwerte!$B$13)^($A16-C$3-1)*C36/C$7),0) | D16: =IF(AND(D$4=1,$A16>D$3,D$7>0),MIN(D36,Startwerte!$B$12*Startwerte!$B$14*(1-Startwerte!$B$13)^($A16-D$3-1)*D36/D$7),0) | E16: =IF(AND(E$4=1,$A16>E$3,E$7>0),MIN(E36,Startwerte!$B$12*Startwerte!$B$14*(1-Startwerte!$B$13)^($A16-E$3-1)*E36/E$7),0) | F16: =IF(AND(F$4=1,$A16>F$3,F$7>0),MIN(F36,Startwerte!$B$12*Startwerte!$B$14*(1-Startwerte!$B$13)^($A16-F$3-1)*F36/F$7),0) | G16: =IF(AND(G$4=1,$A16>G$3,G$7>0),MIN(G36,Startwerte!$B$12*Startwerte!$B$14*(1-Startwerte!$B$13)^($A16-G$3-1)*G36/G$7),0) | H16: =IF(AND(H$4=1,$A16>H$3,H$7>0),MIN(H36,Startwerte!$B$12*Startwerte!$B$14*(1-Startwerte!$B$13)^($A16-H$3-1)*H36/H$7),0) | I16: =IF(AND(I$4=1,$A16>I$3,I$7>0),MIN(I36,Startwerte!$B$12*Startwerte!$B$14*(1-Startwerte!$B$13)^($A16-I$3-1)*I36/I$7),0) | ... Q16: =IF(AND(Q$4=1,$A16>Q$3,Q$7>0),MIN(Q36,Startwerte!$B$12*Startwerte!$B$14*(1-Startwerte!$B$13)^($A16-Q$3-1)*Q36/Q$7),0)
A17: 8 | B17: =IF(AND(B$4=1,$A17>B$3,B$7>0),MIN(B37,Startwerte!$B$12*Startwerte!$B$14*(1-Startwerte!$B$13)^($A17-B$3-1)*B37/B$7),0) | C17: =IF(AND(C$4=1,$A17>C$3,C$7>0),MIN(C37,Startwerte!$B$12*Startwerte!$B$14*(1-Startwerte!$B$13)^($A17-C$3-1)*C37/C$7),0) | D17: =IF(AND(D$4=1,$A17>D$3,D$7>0),MIN(D37,Startwerte!$B$12*Startwerte!$B$14*(1-Startwerte!$B$13)^($A17-D$3-1)*D37/D$7),0) | E17: =IF(AND(E$4=1,$A17>E$3,E$7>0),MIN(E37,Startwerte!$B$12*Startwerte!$B$14*(1-Startwerte!$B$13)^($A17-E$3-1)*E37/E$7),0) | F17: =IF(AND(F$4=1,$A17>F$3,F$7>0),MIN(F37,Startwerte!$B$12*Startwerte!$B$14*(1-Startwerte!$B$13)^($A17-F$3-1)*F37/F$7),0) | G17: =IF(AND(G$4=1,$A17>G$3,G$7>0),MIN(G37,Startwerte!$B$12*Startwerte!$B$14*(1-Startwerte!$B$13)^($A17-G$3-1)*G37/G$7),0) | H17: =IF(AND(H$4=1,$A17>H$3,H$7>0),MIN(H37,Startwerte!$B$12*Startwerte!$B$14*(1-Startwerte!$B$13)^($A17-H$3-1)*H37/H$7),0) | I17: =IF(AND(I$4=1,$A17>I$3,I$7>0),MIN(I37,Startwerte!$B$12*Startwerte!$B$14*(1-Startwerte!$B$13)^($A17-I$3-1)*I37/I$7),0) | ... Q17: =IF(AND(Q$4=1,$A17>Q$3,Q$7>0),MIN(Q37,Startwerte!$B$12*Startwerte!$B$14*(1-Startwerte!$B$13)^($A17-Q$3-1)*Q37/Q$7),0)
A18: 9 | B18: =IF(AND(B$4=1,$A18>B$3,B$7>0),MIN(B38,Startwerte!$B$12*Startwerte!$B$14*(1-Startwerte!$B$13)^($A18-B$3-1)*B38/B$7),0) | C18: =IF(AND(C$4=1,$A18>C$3,C$7>0),MIN(C38,Startwerte!$B$12*Startwerte!$B$14*(1-Startwerte!$B$13)^($A18-C$3-1)*C38/C$7),0) | D18: =IF(AND(D$4=1,$A18>D$3,D$7>0),MIN(D38,Startwerte!$B$12*Startwerte!$B$14*(1-Startwerte!$B$13)^($A18-D$3-1)*D38/D$7),0) | E18: =IF(AND(E$4=1,$A18>E$3,E$7>0),MIN(E38,Startwerte!$B$12*Startwerte!$B$14*(1-Startwerte!$B$13)^($A18-E$3-1)*E38/E$7),0) | F18: =IF(AND(F$4=1,$A18>F$3,F$7>0),MIN(F38,Startwerte!$B$12*Startwerte!$B$14*(1-Startwerte!$B$13)^($A18-F$3-1)*F38/F$7),0) | G18: =IF(AND(G$4=1,$A18>G$3,G$7>0),MIN(G38,Startwerte!$B$12*Startwerte!$B$14*(1-Startwerte!$B$13)^($A18-G$3-1)*G38/G$7),0) | H18: =IF(AND(H$4=1,$A18>H$3,H$7>0),MIN(H38,Startwerte!$B$12*Startwerte!$B$14*(1-Startwerte!$B$13)^($A18-H$3-1)*H38/H$7),0) | I18: =IF(AND(I$4=1,$A18>I$3,I$7>0),MIN(I38,Startwerte!$B$12*Startwerte!$B$14*(1-Startwerte!$B$13)^($A18-I$3-1)*I38/I$7),0) | ... Q18: =IF(AND(Q$4=1,$A18>Q$3,Q$7>0),MIN(Q38,Startwerte!$B$12*Startwerte!$B$14*(1-Startwerte!$B$13)^($A18-Q$3-1)*Q38/Q$7),0)
A19: 10 | B19: =IF(AND(B$4=1,$A19>B$3,B$7>0),MIN(B39,Startwerte!$B$12*Startwerte!$B$14*(1-Startwerte!$B$13)^($A19-B$3-1)*B39/B$7),0) | C19: =IF(AND(C$4=1,$A19>C$3,C$7>0),MIN(C39,Startwerte!$B$12*Startwerte!$B$14*(1-Startwerte!$B$13)^($A19-C$3-1)*C39/C$7),0) | D19: =IF(AND(D$4=1,$A19>D$3,D$7>0),MIN(D39,Startwerte!$B$12*Startwerte!$B$14*(1-Startwerte!$B$13)^($A19-D$3-1)*D39/D$7),0) | E19: =IF(AND(E$4=1,$A19>E$3,E$7>0),MIN(E39,Startwerte!$B$12*Startwerte!$B$14*(1-Startwerte!$B$13)^($A19-E$3-1)*E39/E$7),0) | F19: =IF(AND(F$4=1,$A19>F$3,F$7>0),MIN(F39,Startwerte!$B$12*Startwerte!$B$14*(1-Startwerte!$B$13)^($A19-F$3-1)*F39/F$7),0) | G19: =IF(AND(G$4=1,$A19>G$3,G$7>0),MIN(G39,Startwerte!$B$12*Startwerte!$B$14*(1-Startwerte!$B$13)^($A19-G$3-1)*G39/G$7),0) | H19: =IF(AND(H$4=1,$A19>H$3,H$7>0),MIN(H39,Startwerte!$B$12*Startwerte!$B$14*(1-Startwerte!$B$13)^($A19-H$3-1)*H39/H$7),0) | I19: =IF(AND(I$4=1,$A19>I$3,I$7>0),MIN(I39,Startwerte!$B$12*Startwerte!$B$14*(1-Startwerte!$B$13)^($A19-I$3-1)*I39/I$7),0) | ... Q19: =IF(AND(Q$4=1,$A19>Q$3,Q$7>0),MIN(Q39,Startwerte!$B$12*Startwerte!$B$14*(1-Startwerte!$B$13)^($A19-Q$3-1)*Q39/Q$7),0)
A20: 11 | B20: =IF(AND(B$4=1,$A20>B$3,B$7>0),MIN(B40,Startwerte!$B$12*Startwerte!$B$14*(1-Startwerte!$B$13)^($A20-B$3-1)*B40/B$7),0) | C20: =IF(AND(C$4=1,$A20>C$3,C$7>0),MIN(C40,Startwerte!$B$12*Startwerte!$B$14*(1-Startwerte!$B$13)^($A20-C$3-1)*C40/C$7),0) | D20: =IF(AND(D$4=1,$A20>D$3,D$7>0),MIN(D40,Startwerte!$B$12*Startwerte!$B$14*(1-Startwerte!$B$13)^($A20-D$3-1)*D40/D$7),0) | E20: =IF(AND(E$4=1,$A20>E$3,E$7>0),MIN(E40,Startwerte!$B$12*Startwerte!$B$14*(1-Startwerte!$B$13)^($A20-E$3-1)*E40/E$7),0) | F20: =IF(AND(F$4=1,$A20>F$3,F$7>0),MIN(F40,Startwerte!$B$12*Startwerte!$B$14*(1-Startwerte!$B$13)^($A20-F$3-1)*F40/F$7),0) | G20: =IF(AND(G$4=1,$A20>G$3,G$7>0),MIN(G40,Startwerte!$B$12*Startwerte!$B$14*(1-Startwerte!$B$13)^($A20-G$3-1)*G40/G$7),0) | H20: =IF(AND(H$4=1,$A20>H$3,H$7>0),MIN(H40,Startwerte!$B$12*Startwerte!$B$14*(1-Startwerte!$B$13)^($A20-H$3-1)*H40/H$7),0) | I20: =IF(AND(I$4=1,$A20>I$3,I$7>0),MIN(I40,Startwerte!$B$12*Startwerte!$B$14*(1-Startwerte!$B$13)^($A20-I$3-1)*I40/I$7),0) | ... Q20: =IF(AND(Q$4=1,$A20>Q$3,Q$7>0),MIN(Q40,Startwerte!$B$12*Startwerte!$B$14*(1-Startwerte!$B$13)^($A20-Q$3-1)*Q40/Q$7),0)
A21: 12 | B21: =IF(AND(B$4=1,$A21>B$3,B$7>0),MIN(B41,Startwerte!$B$12*Startwerte!$B$14*(1-Startwerte!$B$13)^($A21-B$3-1)*B41/B$7),0) | C21: =IF(AND(C$4=1,$A21>C$3,C$7>0),MIN(C41,Startwerte!$B$12*Startwerte!$B$14*(1-Startwerte!$B$13)^($A21-C$3-1)*C41/C$7),0) | D21: =IF(AND(D$4=1,$A21>D$3,D$7>0),MIN(D41,Startwerte!$B$12*Startwerte!$B$14*(1-Startwerte!$B$13)^($A21-D$3-1)*D41/D$7),0) | E21: =IF(AND(E$4=1,$A21>E$3,E$7>0),MIN(E41,Startwerte!$B$12*Startwerte!$B$14*(1-Startwerte!$B$13)^($A21-E$3-1)*E41/E$7),0) | F21: =IF(AND(F$4=1,$A21>F$3,F$7>0),MIN(F41,Startwerte!$B$12*Startwerte!$B$14*(1-Startwerte!$B$13)^($A21-F$3-1)*F41/F$7),0) | G21: =IF(AND(G$4=1,$A21>G$3,G$7>0),MIN(G41,Startwerte!$B$12*Startwerte!$B$14*(1-Startwerte!$B$13)^($A21-G$3-1)*G41/G$7),0) | H21: =IF(AND(H$4=1,$A21>H$3,H$7>0),MIN(H41,Startwerte!$B$12*Startwerte!$B$14*(1-Startwerte!$B$13)^($A21-H$3-1)*H41/H$7),0) | I21: =IF(AND(I$4=1,$A21>I$3,I$7>0),MIN(I41,Startwerte!$B$12*Startwerte!$B$14*(1-Startwerte!$B$13)^($A21-I$3-1)*I41/I$7),0) | ... Q21: =IF(AND(Q$4=1,$A21>Q$3,Q$7>0),MIN(Q41,Startwerte!$B$12*Startwerte!$B$14*(1-Startwerte!$B$13)^($A21-Q$3-1)*Q41/Q$7),0)
... A25: 16 | B25: =IF(AND(B$4=1,$A25>B$3,B$7>0),MIN(B45,Startwerte!$B$12*Startwerte!$B$14*(1-Startwerte!$B$13)^($A25-B$3-1)*B45/B$7),0) | C25: =IF(AND(C$4=1,$A25>C$3,C$7>0),MIN(C45,Startwerte!$B$12*Startwerte!$B$14*(1-Startwerte!$B$13)^($A25-C$3-1)*C45/C$7),0) | D25: =IF(AND(D$4=1,$A25>D$3,D$7>0),MIN(D45,Startwerte!$B$12*Startwerte!$B$14*(1-Startwerte!$B$13)^($A25-D$3-1)*D45/D$7),0) | E25: =IF(AND(E$4=1,$A25>E$3,E$7>0),MIN(E45,Startwerte!$B$12*Startwerte!$B$14*(1-Startwerte!$B$13)^($A25-E$3-1)*E45/E$7),0) | F25: =IF(AND(F$4=1,$A25>F$3,F$7>0),MIN(F45,Startwerte!$B$12*Startwerte!$B$14*(1-Startwerte!$B$13)^($A25-F$3-1)*F45/F$7),0) | G25: =IF(AND(G$4=1,$A25>G$3,G$7>0),MIN(G45,Startwerte!$B$12*Startwerte!$B$14*(1-Startwerte!$B$13)^($A25-G$3-1)*G45/G$7),0) | H25: =IF(AND(H$4=1,$A25>H$3,H$7>0),MIN(H45,Startwerte!$B$12*Startwerte!$B$14*(1-Startwerte!$B$13)^($A25-H$3-1)*H45/H$7),0) | I25: =IF(AND(I$4=1,$A25>I$3,I$7>0),MIN(I45,Startwerte!$B$12*Startwerte!$B$14*(1-Startwerte!$B$13)^($A25-I$3-1)*I45/I$7),0) | ... Q25: =IF(AND(Q$4=1,$A25>Q$3,Q$7>0),MIN(Q45,Startwerte!$B$12*Startwerte!$B$14*(1-Startwerte!$B$13)^($A25-Q$3-1)*Q45/Q$7),0)
A29: Restreserve zu Rundenbeginn (bbl)
A30: 1 | B30: =B$7 | C30: =C$7 | D30: =D$7 | E30: =E$7 | F30: =F$7 | G30: =G$7 | H30: =H$7 | I30: =I$7 | ... Q30: =Q$7
A31: 2 | B31: =B30-B10 | C31: =C30-C10 | D31: =D30-D10 | E31: =E30-E10 | F31: =F30-F10 | G31: =G30-G10 | H31: =H30-H10 | I31: =I30-I10 | ... Q31: =Q30-Q10
A32: 3 | B32: =B31-B11 | C32: =C31-C11 | D32: =D31-D11 | E32: =E31-E11 | F32: =F31-F11 | G32: =G31-G11 | H32: =H31-H11 | I32: =I31-I11 | ... Q32: =Q31-Q11
A33: 4 | B33: =B32-B12 | C33: =C32-C12 | D33: =D32-D12 | E33: =E32-E12 | F33: =F32-F12 | G33: =G32-G12 | H33: =H32-H12 | I33: =I32-I12 | ... Q33: =Q32-Q12
A34: 5 | B34: =B33-B13 | C34: =C33-C13 | D34: =D33-D13 | E34: =E33-E13 | F34: =F33-F13 | G34: =G33-G13 | H34: =H33-H13 | I34: =I33-I13 | ... Q34: =Q33-Q13
A35: 6 | B35: =B34-B14 | C35: =C34-C14 | D35: =D34-D14 | E35: =E34-E14 | F35: =F34-F14 | G35: =G34-G14 | H35: =H34-H14 | I35: =I34-I14 | ... Q35: =Q34-Q14
A36: 7 | B36: =B35-B15 | C36: =C35-C15 | D36: =D35-D15 | E36: =E35-E15 | F36: =F35-F15 | G36: =G35-G15 | H36: =H35-H15 | I36: =I35-I15 | ... Q36: =Q35-Q15
A37: 8 | B37: =B36-B16 | C37: =C36-C16 | D37: =D36-D16 | E37: =E36-E16 | F37: =F36-F16 | G37: =G36-G16 | H37: =H36-H16 | I37: =I36-I16 | ... Q37: =Q36-Q16
A38: 9 | B38: =B37-B17 | C38: =C37-C17 | D38: =D37-D17 | E38: =E37-E17 | F38: =F37-F17 | G38: =G37-G17 | H38: =H37-H17 | I38: =I37-I17 | ... Q38: =Q37-Q17
A39: 10 | B39: =B38-B18 | C39: =C38-C18 | D39: =D38-D18 | E39: =E38-E18 | F39: =F38-F18 | G39: =G38-G18 | H39: =H38-H18 | I39: =I38-I18 | ... Q39: =Q38-Q18
A40: 11 | B40: =B39-B19 | C40: =C39-C19 | D40: =D39-D19 | E40: =E39-E19 | F40: =F39-F19 | G40: =G39-G19 | H40: =H39-H19 | I40: =I39-I19 | ... Q40: =Q39-Q19
A41: 12 | B41: =B40-B20 | C41: =C40-C20 | D41: =D40-D20 | E41: =E40-E20 | F41: =F40-F20 | G41: =G40-G20 | H41: =H40-H20 | I41: =I40-I20 | ... Q41: =Q40-Q20
A42: 13 | B42: =B41-B21 | C42: =C41-C21 | D42: =D41-D21 | E42: =E41-E21 | F42: =F41-F21 | G42: =G41-G21 | H42: =H41-H21 | I42: =I41-I21 | ... Q42: =Q41-Q21
... A45: 16 | B45: =B44-B24 | C45: =C44-C24 | D45: =D44-D24 | E45: =E44-E24 | F45: =F44-F24 | G45: =G44-G24 | H45: =H44-H24 | I45: =I44-I24 | ... Q45: =Q44-Q24

Sheet Pleiterechner
A1: Pleiterechner: Wie viele Trockenbohrungen hält Jacob aus?
A2: Annahme: Pechsträhne – jede Runde eine neue Parzelle pachten und bohren, alles trocken. Pachtbonus, Startgeld, Zins und freie Pachtoptionen kommen aus „Startwerte“. Bohrkosten (Zeilen) und Kreditrahmen (Spalten) sind hier frei wählbar.
A4: Bezahlbare Trockenbohrungen, bevor Jacob pleite ist
B5: Bohrkosten ↓ / Kreditrahmen → | C5: 0 | D5: 3000 | E5: 6000 | F5: 10000
B6: 1500 | C6: =SUMPRODUCT((B24:B39<=(Startwerte!$B$5+B$23))*1) | D6: =SUMPRODUCT((C24:C39<=(Startwerte!$B$5+C$23))*1) | E6: =SUMPRODUCT((D24:D39<=(Startwerte!$B$5+D$23))*1) | F6: =SUMPRODUCT((E24:E39<=(Startwerte!$B$5+E$23))*1)
B7: 2000 | C7: =SUMPRODUCT((F24:F39<=(Startwerte!$B$5+F$23))*1) | D7: =SUMPRODUCT((G24:G39<=(Startwerte!$B$5+G$23))*1) | E7: =SUMPRODUCT((H24:H39<=(Startwerte!$B$5+H$23))*1) | F7: =SUMPRODUCT((I24:I39<=(Startwerte!$B$5+I$23))*1)
B8: 2500 | C8: =SUMPRODUCT((J24:J39<=(Startwerte!$B$5+J$23))*1) | D8: =SUMPRODUCT((K24:K39<=(Startwerte!$B$5+K$23))*1) | E8: =SUMPRODUCT((L24:L39<=(Startwerte!$B$5+L$23))*1) | F8: =SUMPRODUCT((M24:M39<=(Startwerte!$B$5+M$23))*1)
B9: 3000 | C9: =SUMPRODUCT((N24:N39<=(Startwerte!$B$5+N$23))*1) | D9: =SUMPRODUCT((O24:O39<=(Startwerte!$B$5+O$23))*1) | E9: =SUMPRODUCT((P24:P39<=(Startwerte!$B$5+P$23))*1) | F9: =SUMPRODUCT((Q24:Q39<=(Startwerte!$B$5+Q$23))*1)
A11: Wahrscheinlichkeit, mit all diesen Bohrungen kein Öl zu finden (Trefferquote aus „Startwerte“)
B12: Bohrkosten ↓ / Kreditrahmen → | C12: =C5 | D12: =D5 | E12: =E5 | F12: =F5
B13: =B6 | C13: =(1-Startwerte!$B$20)^C6 | D13: =(1-Startwerte!$B$20)^D6 | E13: =(1-Startwerte!$B$20)^E6 | F13: =(1-Startwerte!$B$20)^F6
B14: =B7 | C14: =(1-Startwerte!$B$20)^C7 | D14: =(1-Startwerte!$B$20)^D7 | E14: =(1-Startwerte!$B$20)^E7 | F14: =(1-Startwerte!$B$20)^F7
B15: =B8 | C15: =(1-Startwerte!$B$20)^C8 | D15: =(1-Startwerte!$B$20)^D8 | E15: =(1-Startwerte!$B$20)^E8 | F15: =(1-Startwerte!$B$20)^F8
B16: =B9 | C16: =(1-Startwerte!$B$20)^C9 | D16: =(1-Startwerte!$B$20)^D9 | E16: =(1-Startwerte!$B$20)^E9 | F16: =(1-Startwerte!$B$20)^F9
A18: Lesart: Bei 2.000 $ Bohrkosten und 3.000 $ Kredit kann Jacob 2 Trockenbohrungen bezahlen; die dritte nicht mehr. Ein Fund rettet ihn nicht sicher – eine „Tasche“ (45 % aller Funde) hat nur 20.000 bbl.
A21: Hilfsrechnung: kumulierte Ausgaben (Bohrung + Pacht + Zinsen) je Szenario
A22: Bohrkosten | B22: =$B$6 | C22: =$B$6 | D22: =$B$6 | E22: =$B$6 | F22: =$B$7 | G22: =$B$7 | H22: =$B$7 | I22: =$B$7 | J22: =$B$8 | K22: =$B$8 | L22: =$B$8 | M22: =$B$8 | N22: =$B$9 | O22: =$B$9 | P22: =$B$9 | Q22: =$B$9
A23: Kreditrahmen | B23: =$C$5 | C23: =$D$5 | D23: =$E$5 | E23: =$F$5 | F23: =$C$5 | G23: =$D$5 | H23: =$E$5 | I23: =$F$5 | J23: =$C$5 | K23: =$D$5 | L23: =$E$5 | M23: =$F$5 | N23: =$C$5 | O23: =$D$5 | P23: =$E$5 | Q23: =$F$5
A24: 1 | B24: =B$22+IF($A24>Startwerte!$B$8,Startwerte!$B$7,0) | C24: =C$22+IF($A24>Startwerte!$B$8,Startwerte!$B$7,0) | D24: =D$22+IF($A24>Startwerte!$B$8,Startwerte!$B$7,0) | E24: =E$22+IF($A24>Startwerte!$B$8,Startwerte!$B$7,0) | F24: =F$22+IF($A24>Startwerte!$B$8,Startwerte!$B$7,0) | G24: =G$22+IF($A24>Startwerte!$B$8,Startwerte!$B$7,0) | H24: =H$22+IF($A24>Startwerte!$B$8,Startwerte!$B$7,0) | I24: =I$22+IF($A24>Startwerte!$B$8,Startwerte!$B$7,0) | ... Q24: =Q$22+IF($A24>Startwerte!$B$8,Startwerte!$B$7,0)
A25: 2 | B25: =B24+B$22+IF($A25>Startwerte!$B$8,Startwerte!$B$7,0)+MAX(0,B24-Startwerte!$B$5)*Startwerte!$B$18/4 | C25: =C24+C$22+IF($A25>Startwerte!$B$8,Startwerte!$B$7,0)+MAX(0,C24-Startwerte!$B$5)*Startwerte!$B$18/4 | D25: =D24+D$22+IF($A25>Startwerte!$B$8,Startwerte!$B$7,0)+MAX(0,D24-Startwerte!$B$5)*Startwerte!$B$18/4 | E25: =E24+E$22+IF($A25>Startwerte!$B$8,Startwerte!$B$7,0)+MAX(0,E24-Startwerte!$B$5)*Startwerte!$B$18/4 | F25: =F24+F$22+IF($A25>Startwerte!$B$8,Startwerte!$B$7,0)+MAX(0,F24-Startwerte!$B$5)*Startwerte!$B$18/4 | G25: =G24+G$22+IF($A25>Startwerte!$B$8,Startwerte!$B$7,0)+MAX(0,G24-Startwerte!$B$5)*Startwerte!$B$18/4 | H25: =H24+H$22+IF($A25>Startwerte!$B$8,Startwerte!$B$7,0)+MAX(0,H24-Startwerte!$B$5)*Startwerte!$B$18/4 | I25: =I24+I$22+IF($A25>Startwerte!$B$8,Startwerte!$B$7,0)+MAX(0,I24-Startwerte!$B$5)*Startwerte!$B$18/4 | ... Q25: =Q24+Q$22+IF($A25>Startwerte!$B$8,Startwerte!$B$7,0)+MAX(0,Q24-Startwerte!$B$5)*Startwerte!$B$18/4
A26: 3 | B26: =B25+B$22+IF($A26>Startwerte!$B$8,Startwerte!$B$7,0)+MAX(0,B25-Startwerte!$B$5)*Startwerte!$B$18/4 | C26: =C25+C$22+IF($A26>Startwerte!$B$8,Startwerte!$B$7,0)+MAX(0,C25-Startwerte!$B$5)*Startwerte!$B$18/4 | D26: =D25+D$22+IF($A26>Startwerte!$B$8,Startwerte!$B$7,0)+MAX(0,D25-Startwerte!$B$5)*Startwerte!$B$18/4 | E26: =E25+E$22+IF($A26>Startwerte!$B$8,Startwerte!$B$7,0)+MAX(0,E25-Startwerte!$B$5)*Startwerte!$B$18/4 | F26: =F25+F$22+IF($A26>Startwerte!$B$8,Startwerte!$B$7,0)+MAX(0,F25-Startwerte!$B$5)*Startwerte!$B$18/4 | G26: =G25+G$22+IF($A26>Startwerte!$B$8,Startwerte!$B$7,0)+MAX(0,G25-Startwerte!$B$5)*Startwerte!$B$18/4 | H26: =H25+H$22+IF($A26>Startwerte!$B$8,Startwerte!$B$7,0)+MAX(0,H25-Startwerte!$B$5)*Startwerte!$B$18/4 | I26: =I25+I$22+IF($A26>Startwerte!$B$8,Startwerte!$B$7,0)+MAX(0,I25-Startwerte!$B$5)*Startwerte!$B$18/4 | ... Q26: =Q25+Q$22+IF($A26>Startwerte!$B$8,Startwerte!$B$7,0)+MAX(0,Q25-Startwerte!$B$5)*Startwerte!$B$18/4
A27: 4 | B27: =B26+B$22+IF($A27>Startwerte!$B$8,Startwerte!$B$7,0)+MAX(0,B26-Startwerte!$B$5)*Startwerte!$B$18/4 | C27: =C26+C$22+IF($A27>Startwerte!$B$8,Startwerte!$B$7,0)+MAX(0,C26-Startwerte!$B$5)*Startwerte!$B$18/4 | D27: =D26+D$22+IF($A27>Startwerte!$B$8,Startwerte!$B$7,0)+MAX(0,D26-Startwerte!$B$5)*Startwerte!$B$18/4 | E27: =E26+E$22+IF($A27>Startwerte!$B$8,Startwerte!$B$7,0)+MAX(0,E26-Startwerte!$B$5)*Startwerte!$B$18/4 | F27: =F26+F$22+IF($A27>Startwerte!$B$8,Startwerte!$B$7,0)+MAX(0,F26-Startwerte!$B$5)*Startwerte!$B$18/4 | G27: =G26+G$22+IF($A27>Startwerte!$B$8,Startwerte!$B$7,0)+MAX(0,G26-Startwerte!$B$5)*Startwerte!$B$18/4 | H27: =H26+H$22+IF($A27>Startwerte!$B$8,Startwerte!$B$7,0)+MAX(0,H26-Startwerte!$B$5)*Startwerte!$B$18/4 | I27: =I26+I$22+IF($A27>Startwerte!$B$8,Startwerte!$B$7,0)+MAX(0,I26-Startwerte!$B$5)*Startwerte!$B$18/4 | ... Q27: =Q26+Q$22+IF($A27>Startwerte!$B$8,Startwerte!$B$7,0)+MAX(0,Q26-Startwerte!$B$5)*Startwerte!$B$18/4
A28: 5 | B28: =B27+B$22+IF($A28>Startwerte!$B$8,Startwerte!$B$7,0)+MAX(0,B27-Startwerte!$B$5)*Startwerte!$B$18/4 | C28: =C27+C$22+IF($A28>Startwerte!$B$8,Startwerte!$B$7,0)+MAX(0,C27-Startwerte!$B$5)*Startwerte!$B$18/4 | D28: =D27+D$22+IF($A28>Startwerte!$B$8,Startwerte!$B$7,0)+MAX(0,D27-Startwerte!$B$5)*Startwerte!$B$18/4 | E28: =E27+E$22+IF($A28>Startwerte!$B$8,Startwerte!$B$7,0)+MAX(0,E27-Startwerte!$B$5)*Startwerte!$B$18/4 | F28: =F27+F$22+IF($A28>Startwerte!$B$8,Startwerte!$B$7,0)+MAX(0,F27-Startwerte!$B$5)*Startwerte!$B$18/4 | G28: =G27+G$22+IF($A28>Startwerte!$B$8,Startwerte!$B$7,0)+MAX(0,G27-Startwerte!$B$5)*Startwerte!$B$18/4 | H28: =H27+H$22+IF($A28>Startwerte!$B$8,Startwerte!$B$7,0)+MAX(0,H27-Startwerte!$B$5)*Startwerte!$B$18/4 | I28: =I27+I$22+IF($A28>Startwerte!$B$8,Startwerte!$B$7,0)+MAX(0,I27-Startwerte!$B$5)*Startwerte!$B$18/4 | ... Q28: =Q27+Q$22+IF($A28>Startwerte!$B$8,Startwerte!$B$7,0)+MAX(0,Q27-Startwerte!$B$5)*Startwerte!$B$18/4
A29: 6 | B29: =B28+B$22+IF($A29>Startwerte!$B$8,Startwerte!$B$7,0)+MAX(0,B28-Startwerte!$B$5)*Startwerte!$B$18/4 | C29: =C28+C$22+IF($A29>Startwerte!$B$8,Startwerte!$B$7,0)+MAX(0,C28-Startwerte!$B$5)*Startwerte!$B$18/4 | D29: =D28+D$22+IF($A29>Startwerte!$B$8,Startwerte!$B$7,0)+MAX(0,D28-Startwerte!$B$5)*Startwerte!$B$18/4 | E29: =E28+E$22+IF($A29>Startwerte!$B$8,Startwerte!$B$7,0)+MAX(0,E28-Startwerte!$B$5)*Startwerte!$B$18/4 | F29: =F28+F$22+IF($A29>Startwerte!$B$8,Startwerte!$B$7,0)+MAX(0,F28-Startwerte!$B$5)*Startwerte!$B$18/4 | G29: =G28+G$22+IF($A29>Startwerte!$B$8,Startwerte!$B$7,0)+MAX(0,G28-Startwerte!$B$5)*Startwerte!$B$18/4 | H29: =H28+H$22+IF($A29>Startwerte!$B$8,Startwerte!$B$7,0)+MAX(0,H28-Startwerte!$B$5)*Startwerte!$B$18/4 | I29: =I28+I$22+IF($A29>Startwerte!$B$8,Startwerte!$B$7,0)+MAX(0,I28-Startwerte!$B$5)*Startwerte!$B$18/4 | ... Q29: =Q28+Q$22+IF($A29>Startwerte!$B$8,Startwerte!$B$7,0)+MAX(0,Q28-Startwerte!$B$5)*Startwerte!$B$18/4
A30: 7 | B30: =B29+B$22+IF($A30>Startwerte!$B$8,Startwerte!$B$7,0)+MAX(0,B29-Startwerte!$B$5)*Startwerte!$B$18/4 | C30: =C29+C$22+IF($A30>Startwerte!$B$8,Startwerte!$B$7,0)+MAX(0,C29-Startwerte!$B$5)*Startwerte!$B$18/4 | D30: =D29+D$22+IF($A30>Startwerte!$B$8,Startwerte!$B$7,0)+MAX(0,D29-Startwerte!$B$5)*Startwerte!$B$18/4 | E30: =E29+E$22+IF($A30>Startwerte!$B$8,Startwerte!$B$7,0)+MAX(0,E29-Startwerte!$B$5)*Startwerte!$B$18/4 | F30: =F29+F$22+IF($A30>Startwerte!$B$8,Startwerte!$B$7,0)+MAX(0,F29-Startwerte!$B$5)*Startwerte!$B$18/4 | G30: =G29+G$22+IF($A30>Startwerte!$B$8,Startwerte!$B$7,0)+MAX(0,G29-Startwerte!$B$5)*Startwerte!$B$18/4 | H30: =H29+H$22+IF($A30>Startwerte!$B$8,Startwerte!$B$7,0)+MAX(0,H29-Startwerte!$B$5)*Startwerte!$B$18/4 | I30: =I29+I$22+IF($A30>Startwerte!$B$8,Startwerte!$B$7,0)+MAX(0,I29-Startwerte!$B$5)*Startwerte!$B$18/4 | ... Q30: =Q29+Q$22+IF($A30>Startwerte!$B$8,Startwerte!$B$7,0)+MAX(0,Q29-Startwerte!$B$5)*Startwerte!$B$18/4
A31: 8 | B31: =B30+B$22+IF($A31>Startwerte!$B$8,Startwerte!$B$7,0)+MAX(0,B30-Startwerte!$B$5)*Startwerte!$B$18/4 | C31: =C30+C$22+IF($A31>Startwerte!$B$8,Startwerte!$B$7,0)+MAX(0,C30-Startwerte!$B$5)*Startwerte!$B$18/4 | D31: =D30+D$22+IF($A31>Startwerte!$B$8,Startwerte!$B$7,0)+MAX(0,D30-Startwerte!$B$5)*Startwerte!$B$18/4 | E31: =E30+E$22+IF($A31>Startwerte!$B$8,Startwerte!$B$7,0)+MAX(0,E30-Startwerte!$B$5)*Startwerte!$B$18/4 | F31: =F30+F$22+IF($A31>Startwerte!$B$8,Startwerte!$B$7,0)+MAX(0,F30-Startwerte!$B$5)*Startwerte!$B$18/4 | G31: =G30+G$22+IF($A31>Startwerte!$B$8,Startwerte!$B$7,0)+MAX(0,G30-Startwerte!$B$5)*Startwerte!$B$18/4 | H31: =H30+H$22+IF($A31>Startwerte!$B$8,Startwerte!$B$7,0)+MAX(0,H30-Startwerte!$B$5)*Startwerte!$B$18/4 | I31: =I30+I$22+IF($A31>Startwerte!$B$8,Startwerte!$B$7,0)+MAX(0,I30-Startwerte!$B$5)*Startwerte!$B$18/4 | ... Q31: =Q30+Q$22+IF($A31>Startwerte!$B$8,Startwerte!$B$7,0)+MAX(0,Q30-Startwerte!$B$5)*Startwerte!$B$18/4
A32: 9 | B32: =B31+B$22+IF($A32>Startwerte!$B$8,Startwerte!$B$7,0)+MAX(0,B31-Startwerte!$B$5)*Startwerte!$B$18/4 | C32: =C31+C$22+IF($A32>Startwerte!$B$8,Startwerte!$B$7,0)+MAX(0,C31-Startwerte!$B$5)*Startwerte!$B$18/4 | D32: =D31+D$22+IF($A32>Startwerte!$B$8,Startwerte!$B$7,0)+MAX(0,D31-Startwerte!$B$5)*Startwerte!$B$18/4 | E32: =E31+E$22+IF($A32>Startwerte!$B$8,Startwerte!$B$7,0)+MAX(0,E31-Startwerte!$B$5)*Startwerte!$B$18/4 | F32: =F31+F$22+IF($A32>Startwerte!$B$8,Startwerte!$B$7,0)+MAX(0,F31-Startwerte!$B$5)*Startwerte!$B$18/4 | G32: =G31+G$22+IF($A32>Startwerte!$B$8,Startwerte!$B$7,0)+MAX(0,G31-Startwerte!$B$5)*Startwerte!$B$18/4 | H32: =H31+H$22+IF($A32>Startwerte!$B$8,Startwerte!$B$7,0)+MAX(0,H31-Startwerte!$B$5)*Startwerte!$B$18/4 | I32: =I31+I$22+IF($A32>Startwerte!$B$8,Startwerte!$B$7,0)+MAX(0,I31-Startwerte!$B$5)*Startwerte!$B$18/4 | ... Q32: =Q31+Q$22+IF($A32>Startwerte!$B$8,Startwerte!$B$7,0)+MAX(0,Q31-Startwerte!$B$5)*Startwerte!$B$18/4
A33: 10 | B33: =B32+B$22+IF($A33>Startwerte!$B$8,Startwerte!$B$7,0)+MAX(0,B32-Startwerte!$B$5)*Startwerte!$B$18/4 | C33: =C32+C$22+IF($A33>Startwerte!$B$8,Startwerte!$B$7,0)+MAX(0,C32-Startwerte!$B$5)*Startwerte!$B$18/4 | D33: =D32+D$22+IF($A33>Startwerte!$B$8,Startwerte!$B$7,0)+MAX(0,D32-Startwerte!$B$5)*Startwerte!$B$18/4 | E33: =E32+E$22+IF($A33>Startwerte!$B$8,Startwerte!$B$7,0)+MAX(0,E32-Startwerte!$B$5)*Startwerte!$B$18/4 | F33: =F32+F$22+IF($A33>Startwerte!$B$8,Startwerte!$B$7,0)+MAX(0,F32-Startwerte!$B$5)*Startwerte!$B$18/4 | G33: =G32+G$22+IF($A33>Startwerte!$B$8,Startwerte!$B$7,0)+MAX(0,G32-Startwerte!$B$5)*Startwerte!$B$18/4 | H33: =H32+H$22+IF($A33>Startwerte!$B$8,Startwerte!$B$7,0)+MAX(0,H32-Startwerte!$B$5)*Startwerte!$B$18/4 | I33: =I32+I$22+IF($A33>Startwerte!$B$8,Startwerte!$B$7,0)+MAX(0,I32-Startwerte!$B$5)*Startwerte!$B$18/4 | ... Q33: =Q32+Q$22+IF($A33>Startwerte!$B$8,Startwerte!$B$7,0)+MAX(0,Q32-Startwerte!$B$5)*Startwerte!$B$18/4
A34: 11 | B34: =B33+B$22+IF($A34>Startwerte!$B$8,Startwerte!$B$7,0)+MAX(0,B33-Startwerte!$B$5)*Startwerte!$B$18/4 | C34: =C33+C$22+IF($A34>Startwerte!$B$8,Startwerte!$B$7,0)+MAX(0,C33-Startwerte!$B$5)*Startwerte!$B$18/4 | D34: =D33+D$22+IF($A34>Startwerte!$B$8,Startwerte!$B$7,0)+MAX(0,D33-Startwerte!$B$5)*Startwerte!$B$18/4 | E34: =E33+E$22+IF($A34>Startwerte!$B$8,Startwerte!$B$7,0)+MAX(0,E33-Startwerte!$B$5)*Startwerte!$B$18/4 | F34: =F33+F$22+IF($A34>Startwerte!$B$8,Startwerte!$B$7,0)+MAX(0,F33-Startwerte!$B$5)*Startwerte!$B$18/4 | G34: =G33+G$22+IF($A34>Startwerte!$B$8,Startwerte!$B$7,0)+MAX(0,G33-Startwerte!$B$5)*Startwerte!$B$18/4 | H34: =H33+H$22+IF($A34>Startwerte!$B$8,Startwerte!$B$7,0)+MAX(0,H33-Startwerte!$B$5)*Startwerte!$B$18/4 | I34: =I33+I$22+IF($A34>Startwerte!$B$8,Startwerte!$B$7,0)+MAX(0,I33-Startwerte!$B$5)*Startwerte!$B$18/4 | ... Q34: =Q33+Q$22+IF($A34>Startwerte!$B$8,Startwerte!$B$7,0)+MAX(0,Q33-Startwerte!$B$5)*Startwerte!$B$18/4
A35: 12 | B35: =B34+B$22+IF($A35>Startwerte!$B$8,Startwerte!$B$7,0)+MAX(0,B34-Startwerte!$B$5)*Startwerte!$B$18/4 | C35: =C34+C$22+IF($A35>Startwerte!$B$8,Startwerte!$B$7,0)+MAX(0,C34-Startwerte!$B$5)*Startwerte!$B$18/4 | D35: =D34+D$22+IF($A35>Startwerte!$B$8,Startwerte!$B$7,0)+MAX(0,D34-Startwerte!$B$5)*Startwerte!$B$18/4 | E35: =E34+E$22+IF($A35>Startwerte!$B$8,Startwerte!$B$7,0)+MAX(0,E34-Startwerte!$B$5)*Startwerte!$B$18/4 | F35: =F34+F$22+IF($A35>Startwerte!$B$8,Startwerte!$B$7,0)+MAX(0,F34-Startwerte!$B$5)*Startwerte!$B$18/4 | G35: =G34+G$22+IF($A35>Startwerte!$B$8,Startwerte!$B$7,0)+MAX(0,G34-Startwerte!$B$5)*Startwerte!$B$18/4 | H35: =H34+H$22+IF($A35>Startwerte!$B$8,Startwerte!$B$7,0)+MAX(0,H34-Startwerte!$B$5)*Startwerte!$B$18/4 | I35: =I34+I$22+IF($A35>Startwerte!$B$8,Startwerte!$B$7,0)+MAX(0,I34-Startwerte!$B$5)*Startwerte!$B$18/4 | ... Q35: =Q34+Q$22+IF($A35>Startwerte!$B$8,Startwerte!$B$7,0)+MAX(0,Q34-Startwerte!$B$5)*Startwerte!$B$18/4
A36: 13 | B36: =B35+B$22+IF($A36>Startwerte!$B$8,Startwerte!$B$7,0)+MAX(0,B35-Startwerte!$B$5)*Startwerte!$B$18/4 | C36: =C35+C$22+IF($A36>Startwerte!$B$8,Startwerte!$B$7,0)+MAX(0,C35-Startwerte!$B$5)*Startwerte!$B$18/4 | D36: =D35+D$22+IF($A36>Startwerte!$B$8,Startwerte!$B$7,0)+MAX(0,D35-Startwerte!$B$5)*Startwerte!$B$18/4 | E36: =E35+E$22+IF($A36>Startwerte!$B$8,Startwerte!$B$7,0)+MAX(0,E35-Startwerte!$B$5)*Startwerte!$B$18/4 | F36: =F35+F$22+IF($A36>Startwerte!$B$8,Startwerte!$B$7,0)+MAX(0,F35-Startwerte!$B$5)*Startwerte!$B$18/4 | G36: =G35+G$22+IF($A36>Startwerte!$B$8,Startwerte!$B$7,0)+MAX(0,G35-Startwerte!$B$5)*Startwerte!$B$18/4 | H36: =H35+H$22+IF($A36>Startwerte!$B$8,Startwerte!$B$7,0)+MAX(0,H35-Startwerte!$B$5)*Startwerte!$B$18/4 | I36: =I35+I$22+IF($A36>Startwerte!$B$8,Startwerte!$B$7,0)+MAX(0,I35-Startwerte!$B$5)*Startwerte!$B$18/4 | ... Q36: =Q35+Q$22+IF($A36>Startwerte!$B$8,Startwerte!$B$7,0)+MAX(0,Q35-Startwerte!$B$5)*Startwerte!$B$18/4
... A39: 16 | B39: =B38+B$22+IF($A39>Startwerte!$B$8,Startwerte!$B$7,0)+MAX(0,B38-Startwerte!$B$5)*Startwerte!$B$18/4 | C39: =C38+C$22+IF($A39>Startwerte!$B$8,Startwerte!$B$7,0)+MAX(0,C38-Startwerte!$B$5)*Startwerte!$B$18/4 | D39: =D38+D$22+IF($A39>Startwerte!$B$8,Startwerte!$B$7,0)+MAX(0,D38-Startwerte!$B$5)*Startwerte!$B$18/4 | E39: =E38+E$22+IF($A39>Startwerte!$B$8,Startwerte!$B$7,0)+MAX(0,E38-Startwerte!$B$5)*Startwerte!$B$18/4 | F39: =F38+F$22+IF($A39>Startwerte!$B$8,Startwerte!$B$7,0)+MAX(0,F38-Startwerte!$B$5)*Startwerte!$B$18/4 | G39: =G38+G$22+IF($A39>Startwerte!$B$8,Startwerte!$B$7,0)+MAX(0,G38-Startwerte!$B$5)*Startwerte!$B$18/4 | H39: =H38+H$22+IF($A39>Startwerte!$B$8,Startwerte!$B$7,0)+MAX(0,H38-Startwerte!$B$5)*Startwerte!$B$18/4 | I39: =I38+I$22+IF($A39>Startwerte!$B$8,Startwerte!$B$7,0)+MAX(0,I38-Startwerte!$B$5)*Startwerte!$B$18/4 | ... Q39: =Q38+Q$22+IF($A39>Startwerte!$B$8,Startwerte!$B$7,0)+MAX(0,Q38-Startwerte!$B$5)*Startwerte!$B$18/4
